HwYtVidGrabber.py
hwyvidgrabber-1.5.dist-info/licenses/LICENSE
hwyvidgrabber-1.5.dist-info/METADATA
hwyvidgrabber-1.5.dist-info/WHEEL
hwyvidgrabber-1.5.dist-info/entry_points.txt
hwyvidgrabber-1.5.dist-info/top_level.txt
hwyvidgrabber-1.5.dist-info/RECORD
