Metadata-Version: 2.4
Name: hwyvidgrabber
Version: 1.5
Summary: A YouTube downloader app with GUI
Home-page: https://github.com/MalikHw/HwYtVidGrabber
Author: MalikHw
Author-email: MalikHw <help.malicorporation@gmail.com>
License: MIT
Project-URL: Homepage, https://github.com/MalikHw/HwYtVidGrabber
Project-URL: Bug Reports, https://github.com/MalikHw/HwYtVidGrabber/issues
Project-URL: Source, https://github.com/MalikHw/HwYtVidGrabber
Project-URL: Funding, https://www.ko-fi.com/MalikHw47
Keywords: youtube,downloader,video,audio,mp3,mp4,gui,pyqt6
Classifier: Development Status :: 4 - Beta
Classifier: Intended Audience :: End Users/Desktop
Classifier: License :: OSI Approved :: MIT License
Classifier: Operating System :: OS Independent
Classifier: Programming Language :: Python :: 3
Classifier: Programming Language :: Python :: 3.8
Classifier: Programming Language :: Python :: 3.9
Classifier: Programming Language :: Python :: 3.10
Classifier: Programming Language :: Python :: 3.11
Classifier: Programming Language :: Python :: 3.12
Classifier: Topic :: Multimedia :: Video
Classifier: Topic :: Internet :: WWW/HTTP
Classifier: Environment :: X11 Applications :: Qt
Requires-Python: >=3.8
License-File: LICENSE
Requires-Dist: PyQt6>=6.4.0
Requires-Dist: yt-dlp>=2023.1.6
Provides-Extra: dev
Requires-Dist: pytest>=7.0.0; extra == "dev"
Requires-Dist: black>=22.0.0; extra == "dev"
Requires-Dist: flake8>=4.0.0; extra == "dev"
Requires-Dist: twine>=4.0.0; extra == "dev"
Requires-Dist: build>=0.8.0; extra == "dev"
Dynamic: author
Dynamic: home-page
Dynamic: license-file
Dynamic: requires-python
